pygskin/__init__.py
pygskin/animation.py
pygskin/assets.py
pygskin/camera.py
pygskin/clock.py
pygskin/dialogue.py
pygskin/direction.py
pygskin/easing.py
pygskin/ecs.py
pygskin/func.py
pygskin/game.py
pygskin/gradient.py
pygskin/imgui.py
pygskin/input.py
pygskin/lazy.py
pygskin/parallax.py
pygskin/pubsub.py
pygskin/rect.py
pygskin/screen.py
pygskin/shake.py
pygskin/sparse_array.py
pygskin/spritesheet.py
pygskin/spritestack.py
pygskin/statemachine.py
pygskin/stylesheet.py
pygskin/surface.py
pygskin/text.py
pygskin/tile.py
pygskin/utils.py
pygskin/vector.py
pygskin-0.6.0.dist-info/METADATA
pygskin-0.6.0.dist-info/WHEEL
pygskin-0.6.0.dist-info/licenses/LICENSE.md
pygskin-0.6.0.dist-info/RECORD
