Metadata-Version: 2.4
Name: Pygskin
Version: 0.6.0
Project-URL: homepage, https://github.com/andyhd/pygskin
Project-URL: documentation, https://github.com/andyhd/pygskin/blob/main/README.md
Project-URL: repository, https://github.com/andyhd/pygskin
Project-URL: issues, https://github.com/andyhd/pygskin/issues
Author-email: Andy Driver <andy@pagezero.net>
Maintainer-email: Andy Driver <andy@pagezero.net>
License: MIT
License-File: LICENSE.md
Keywords: framework,game,pygame
Classifier: Development Status :: 3 - Alpha
Classifier: Intended Audience :: Developers
Classifier: License :: OSI Approved :: MIT License
Classifier: Programming Language :: Python :: 3
Classifier: Programming Language :: Python :: 3.12
Classifier: Programming Language :: Python :: 3.13
Classifier: Topic :: Software Development :: Libraries
Requires-Python: >=3.12
Requires-Dist: pygame-ce==2.5.2
